{
    "cards":[
       {
          "id":"100",
	  "title":"someTitle",
          "content":"Remote from GIT",
          "type":"someType",
          "isFavorite":"false",
	  "isDone":"false",
	  "isStarted":"false",
	  "imageUrl":"someUrl",
	  "isActive":"false",
	  "isQuick" : "false"
       },   
       {
          "id":"101",
	   title":"someTitle",
          "content":"Remote from GIT 2",
          "type":"someType",
          "isFavorite":"false",
	  "isDone":"false",
	  "isStarted":"false",
	  "imageUrl":"someUrl",
	  "isActive":"false",
	  "isQuick" : "false"
       }
    ]
 }
